UpbeatLabs_MCP39F521/UpbeatLabs_MCP39F521.py
UpbeatLabs_MCP39F521/__init__.py
UpbeatLabs_MCP39F521-2.0.0.dist-info/LICENSE
UpbeatLabs_MCP39F521-2.0.0.dist-info/METADATA
UpbeatLabs_MCP39F521-2.0.0.dist-info/WHEEL
UpbeatLabs_MCP39F521-2.0.0.dist-info/top_level.txt
UpbeatLabs_MCP39F521-2.0.0.dist-info/RECORD
