Metadata-Version: 2.1
Name: UpbeatLabs-MCP39F521
Version: 2.0.0
Summary: Python library to use with Dr. Wattson Energy Monitoring Board and other MCP39F521 based boards
Home-page: https://github.com/upbeatlabs/UpbeatLabs_Python_MCP39F521
Author: Sridhar Rajagopal
Author-email: sridhar@upbeatlabs.com
License: BSD License
Classifier: Development Status :: 4 - Beta
Classifier: Intended Audience :: Developers
Classifier: License :: OSI Approved :: BSD License
Classifier: Operating System :: POSIX :: Linux
Classifier: Programming Language :: Python :: 2.7
Classifier: Programming Language :: Python :: 3
Classifier: Topic :: Software Development
Classifier: Topic :: System :: Hardware
License-File: LICENSE
Requires-Dist: smbus2
